pytest_factoryboy/__init__.py
pytest_factoryboy/compat.py
pytest_factoryboy/fixture.py
pytest_factoryboy/fixturegen.py
pytest_factoryboy/hooks.py
pytest_factoryboy/plugin.py
pytest_factoryboy/py.typed
pytest_factoryboy-2.8.0.dist-info/AUTHORS.rst
pytest_factoryboy-2.8.0.dist-info/LICENSE.md
pytest_factoryboy-2.8.0.dist-info/METADATA
pytest_factoryboy-2.8.0.dist-info/WHEEL
pytest_factoryboy-2.8.0.dist-info/entry_points.txt
pytest_factoryboy-2.8.0.dist-info/RECORD
